pastemngr/__init__.py
pastemngr/api/__init__.py
pastemngr/api/make_request.py
pastemngr/api/pastebin_api.py
pastemngr/core/__init__.py
pastemngr/core/argument_handler.py
pastemngr/core/config.py
pastemngr/core/controller.py
pastemngr/core/main.py
pastemngr/db/__init__.py
pastemngr/db/connection.py
pastemngr/db/database.py
pastemngr/db/model.sql
pastemngr/parser/__init__.py
pastemngr/parser/dev_key_parser.py
pastemngr-1.1.0.data/data/share/doc/pastemngr/README.md
pastemngr-1.1.0.data/data/share/man/man1/pastemngr.1
pastemngr-1.1.0.data/scripts/pastemngr
pastemngr-1.1.0.dist-info/LICENSE
pastemngr-1.1.0.dist-info/METADATA
pastemngr-1.1.0.dist-info/WHEEL
pastemngr-1.1.0.dist-info/top_level.txt
pastemngr-1.1.0.dist-info/RECORD
