Metadata-Version: 2.1
Name: pastemngr
Version: 1.1.0
Summary: A powerful pastebin manager for the command line.
Home-page: https://github.com/pvpscript/pastemngr
Author: pvpscript
License: UNKNOWN
Keywords: pastebin manager console
Platform: UNKNOWN
Classifier: Environment :: Console
Classifier: Intended Audience :: Developers
Classifier: Intended Audience :: End Users/Desktop
Classifier: Intended Audience :: System Administrators
Classifier: License :: OSI Approved :: GNU General Public License v3 (GPLv3)
Classifier: Operating System :: Unix
Classifier: Programming Language :: Python :: 3
Classifier: Topic :: Utilities
Requires: requests
Requires-Python: >=3.6
